xerenity/__init__.py
xerenity/connection/__init__.py
xerenity/connection/db.py
xerenity/loans/__init__.py
xerenity/loans/loans.py
xerenity/search/__init__.py
xerenity/search/series.py
xerenity-0.1.92.dist-info/licenses/LICENSE
xerenity-0.1.92.dist-info/METADATA
xerenity-0.1.92.dist-info/WHEEL
xerenity-0.1.92.dist-info/top_level.txt
xerenity-0.1.92.dist-info/RECORD
